{
  "annotations": {
    "list": [
      {
        "builtIn": 1,
        "datasource": {
          "type": "grafana",
          "uid": "-- Grafana --"
        },
        "enable": true,
        "hide": true,
        "iconColor": "rgba(0, 211, 255, 1)",
        "name": "Annotations & Alerts",
        "type": "dashboard"
      }
    ]
  },
  "editable": true,
  "fiscalYearStartMonth": 0,
  "graphTooltip": 0,
  "id": 1,
  "links": [],
  "panels": [
    {
      "datasource": {
        "type": "prometheus",
        "uid": "bdfnys7w4av40e"
      },
      "fieldConfig": {
        "defaults": {
          "custom": {
            "hideFrom": {
              "legend": false,
              "tooltip": false,
              "viz": false
            },
            "scaleDistribution": {
              "type": "linear"
            }
          }
        },
        "overrides": []
      },
      "gridPos": {
        "h": 11,
        "w": 12,
        "x": 0,
        "y": 0
      },
      "id": 2,
      "maxPerRow": 2,
      "options": {
        "calculate": false,
        "cellGap": 1,
        "color": {
          "exponent": 0.5,
          "fill": "dark-orange",
          "mode": "scheme",
          "reverse": false,
          "scale": "exponential",
          "scheme": "Spectral",
          "steps": 64
        },
        "exemplars": {
          "color": "rgba(255,0,255,0.7)"
        },
        "filterValues": {
          "le": 1e-9
        },
        "legend": {
          "show": true,
          "showLegend": false
        },
        "rowsFrame": {
          "layout": "auto"
        },
        "tooltip": {
          "mode": "single",
          "showColorScale": false,
          "yHistogram": false
        },
        "yAxis": {
          "axisPlacement": "left",
          "max": "1000000000",
          "min": 100000,
          "reverse": false,
          "unit": "ns"
        }
      },
      "pluginVersion": "10.4.0",
      "repeat": "partition",
      "repeatDirection": "h",
      "targets": [
        {
          "datasource": {
            "type": "prometheus",
            "uid": "bdfnys7w4av40e"
          },
          "editorMode": "code",
          "expr": "sum(increase(consumer_latency_ns_bucket{partition_id=\"$partition\"}[30s])) by (le)",
          "format": "heatmap",
          "instant": false,
          "legendFormat": "__auto",
          "range": true,
          "refId": "A"
        }
      ],
      "title": "Latency histogram partition $partition",
      "type": "heatmap"
    }
  ],
  "refresh": "5s",
  "schemaVersion": 39,
  "tags": [],
  "templating": {
    "list": [
      {
        "current": {
          "selected": false,
          "text": [
            "All"
          ],
          "value": [
            "$__all"
          ]
        },
        "datasource": {
          "type": "prometheus",
          "uid": "bdfnys7w4av40e"
        },
        "definition": "label_values(consumer_latency_ns_bucket,partition_id)",
        "hide": 0,
        "includeAll": true,
        "multi": true,
        "name": "partition",
        "options": [],
        "query": {
          "qryType": 1,
          "query": "label_values(consumer_latency_ns_bucket,partition_id)",
          "refId": "PrometheusVariableQueryEditor-VariableQuery"
        },
        "refresh": 1,
        "regex": "",
        "skipUrlSync": false,
        "sort": 3,
        "type": "query"
      }
    ]
  },
  "time": {
    "from": "now-1h",
    "to": "now"
  },
  "timepicker": {},
  "timezone": "browser",
  "title": "Record latency",
  "uid": "ddfnzrgbz3caod",
  "version": 10,
  "weekStart": ""
}